{
  "$schema": "../gen/schemas/desktop-schema.json",
  "identifier": "default",
  "description": "Capability for the main window",
  "windows": [
    "main",
    "settings",
    "import"
  ],
  "permissions": [
    "core:default",
    "opener:default",
    "opener:allow-open-path",
    "opener:allow-reveal-item-in-dir",
    {
      "identifier": "opener:allow-reveal-item-in-dir",
      "allow": [
        {
          "path": "**"
        }
      ]
    },
    "core:window:default",
    "core:webview:allow-create-webview-window",
    "core:window:allow-start-dragging",
    "core:window:allow-minimize",
    "core:window:allow-maximize",
    "core:window:allow-unmaximize",
    "core:window:allow-toggle-maximize",
    "core:window:allow-close",
    "core:window:allow-set-resizable",
    "keyring:default",
    "fs:default",
    "fs:read-all",
    "fs:write-all",
    "fs:allow-watch",
    "fs:allow-unwatch",
    "fs:allow-exists",
    "fs:allow-mkdir",
    {
      "identifier": "fs:scope",
      "allow": [
        "**",
        "**/.*",
        "**/.*/**"
      ]
    },
    "log:default",
    "http:default",
    {
      "identifier": "http:default",
      "allow": [
        { "url": "http://**" },
        { "url": "https://**" }
      ]
    },
    "os:default",
    "store:default",
    "dialog:allow-open",
    "updater:default",
    "process:allow-restart",
    {
      "identifier": "process:allow-exit",
      "allow": [
        {
          "command": "**"
        }
      ]
    },
    "sql:default",
    {
      "identifier": "sql:allow-execute",
      "allow": [
        "sqlite:response-history.db"
      ]
    },
    {
      "identifier": "sql:allow-select",
      "allow": [
        "sqlite:response-history.db"
      ]
    },
    {
      "identifier": "sql:allow-load",
      "allow": [
        "sqlite:response-history.db"
      ]
    },
    "sentry:default"
  ]
}